litepcie/__init__.py
litepcie/common.py
litepcie/gen.py
litepcie/core/__init__.py
litepcie/core/common.py
litepcie/core/crossbar.py
litepcie/core/endpoint.py
litepcie/core/msi.py
litepcie/frontend/__init__.py
litepcie/frontend/axi.py
litepcie/frontend/dma.py
litepcie/frontend/wishbone.py
litepcie/frontend/ptm/__init__.py
litepcie/frontend/ptm/core.py
litepcie/frontend/ptm/sniffer.py
litepcie/frontend/ptm/sniffer_tap.v
litepcie/phy/__init__.py
litepcie/phy/c5pciephy.py
litepcie/phy/common.py
litepcie/phy/s7pciephy.py
litepcie/phy/uspciephy.py
litepcie/phy/usppciephy.py
litepcie/phy/xilinx_us/axis_iff.v
litepcie/phy/xilinx_us/m_axis_cq_adapt_128b.v
litepcie/phy/xilinx_us/m_axis_cq_adapt_256b.v
litepcie/phy/xilinx_us/m_axis_rc_adapt_128b.v
litepcie/phy/xilinx_us/m_axis_rc_adapt_256b.v
litepcie/phy/xilinx_us/pcie_us_support.v
litepcie/phy/xilinx_us/s_axis_cc_adapt_128b.v
litepcie/phy/xilinx_us/s_axis_cc_adapt_256b.v
litepcie/phy/xilinx_us/s_axis_rq_adapt_128b.v
litepcie/phy/xilinx_us/s_axis_rq_adapt_256b.v
litepcie/phy/xilinx_usp/axis_iff.v
litepcie/phy/xilinx_usp/m_axis_cq_adapt_128b.v
litepcie/phy/xilinx_usp/m_axis_cq_adapt_256b.v
litepcie/phy/xilinx_usp/m_axis_cq_adapt_512b.v
litepcie/phy/xilinx_usp/m_axis_rc_adapt_128b.v
litepcie/phy/xilinx_usp/m_axis_rc_adapt_256b.v
litepcie/phy/xilinx_usp/m_axis_rc_adapt_512b.v
litepcie/phy/xilinx_usp/pcie_usp_support.v
litepcie/phy/xilinx_usp/s_axis_cc_adapt_128b.v
litepcie/phy/xilinx_usp/s_axis_cc_adapt_256b.v
litepcie/phy/xilinx_usp/s_axis_cc_adapt_512b.v
litepcie/phy/xilinx_usp/s_axis_rq_adapt_128b.v
litepcie/phy/xilinx_usp/s_axis_rq_adapt_256b.v
litepcie/phy/xilinx_usp/s_axis_rq_adapt_512b.v
litepcie/software/__init__.py
litepcie/software/kernel/Makefile
litepcie/software/kernel/README
litepcie/software/kernel/config.h
litepcie/software/kernel/flags.h
litepcie/software/kernel/init.sh
litepcie/software/kernel/litepcie.h
litepcie/software/kernel/liteuart.c
litepcie/software/kernel/litex.h
litepcie/software/kernel/main.c
litepcie-2024.12.dist-info/licenses/LICENSE
litepcie-2024.12.dist-info/METADATA
litepcie-2024.12.dist-info/WHEEL
litepcie-2024.12.dist-info/entry_points.txt
litepcie-2024.12.dist-info/top_level.txt
litepcie-2024.12.dist-info/RECORD
